mlflow_wrapper/__init__.py
mlflow_wrapper/experiment_handler.py
mlflow_wrapper/folder_management.py
mlflow_wrapper/run_handler.py
mlflow_wrapper/upload_handler.py
mlflow_wrapper-0.0.1.8.dist-info/LICENSE
mlflow_wrapper-0.0.1.8.dist-info/METADATA
mlflow_wrapper-0.0.1.8.dist-info/WHEEL
mlflow_wrapper-0.0.1.8.dist-info/top_level.txt
mlflow_wrapper-0.0.1.8.dist-info/RECORD
