Metadata-Version: 2.1
Name: mlflow-wrapper
Version: 0.0.1.8
Summary: A mlflow wrapper for easier handling of runs and experiments
Author-email: Exitare <exitare@exitare.de>
License: MIT License        
Project-URL: Homepage, https://github.com/Exitare/mlflow-wrapper
Project-URL: Bug Tracker, https://github.com/Exitare/mlflow-wrapper/issues
Project-URL: Documentation, https://github.com/Exitare/mlflow-wrapper/wiki
Classifier: Programming Language :: Python :: 3
Classifier: License :: OSI Approved :: MIT License
Classifier: Operating System :: OS Independent
Requires-Python: >=3.7
License-File: LICENSE
